{
  "name": "Chordata",
  "children": [
    {
      "name": "Mammalia",
      "children": [
        {"name": "Primate",
          "children": [
            {
              "name": "Lemuridae",
              "children": [
                {
                  "name": "Lemur",
                  "children": [
                    {
                      "name": "Ring-tailed Lemur"
                    }
                  ]
                }
              ]
            },
            {
              "name": "Catarrhini",
              "children": [
                {"name": "Cercopithecoidea"},
                {
                  "name": "Hominoidea",
                  "children": [
                    {"name": "Ponginae"},
                    {"name": "Gorillinae"},
                    {"name": "Homininae"}
                  ]
                }
              ]
            },
            {"name": "Lorisiformes"}
          ]
        },
        {"name": "Marsupialia"},
        {"name": "Cetacea"},
        {"name": "Proboscidea"}
      ]
    },
    {
      "name": "Aves",
      "children": [
        {"name": "Struthioniformes",
          "children": [
            {"name": "Emu"},
            {"name": "Ostrich"},
            {"name": "Kiwi"}
          ]},
        {"name": "Turniciformes"},
        {"name": "Piciformes"}
      ]},
    {"name": "Reptilia"}
  ]
}
